mir/protology.py
mir/termdbg.py
mir/termdbg/__init__.py
mir/termdbg/__main__.py
mir/termdbg/ascii.csv
mir/termdbg/ascii.py
mir/termdbg/ccr.py
mir/termdbg/format.py
mir/termdbg/term.py
mir.termdbg-2.0.0.dist-info/DESCRIPTION.rst
mir.termdbg-2.0.0.dist-info/METADATA
mir.termdbg-2.0.0.dist-info/RECORD
mir.termdbg-2.0.0.dist-info/WHEEL
mir.termdbg-2.0.0.dist-info/metadata.json
mir.termdbg-2.0.0.dist-info/top_level.txt
