Metadata-Version: 2.0
Name: mir.termdbg
Version: 2.0.0
Summary: Terminal debugging tools
Home-page: https://github.com/darkfeline/mir.termdbg
Author: Allen Li
Author-email: darkfeline@felesatra.moe
License: UNKNOWN
Platform: UNKNOWN
Classifier: Development Status :: 4 - Beta
Classifier: Intended Audience :: Developers
Classifier: License :: OSI Approved :: Apache Software License
Classifier: Programming Language :: Python :: 3.6
